ankml/__init__.py
ankml/cli.py
ankml/config.py
ankml/exceptions.py
ankml/features.py
ankml/loader.py
ankml/predictor.py
ankml-1.0.7.dist-info/METADATA
ankml-1.0.7.dist-info/WHEEL
ankml-1.0.7.dist-info/entry_points.txt
ankml-1.0.7.dist-info/top_level.txt
ankml-1.0.7.dist-info/RECORD
