Metadata-Version: 2.1
Name: ankml
Version: 1.0.7
Summary: Advanced Neural Knowledge for Malware Learning - 恶意软件检测库
Home-page: https://ankml.top
Author: ANKML Team
Author-email: AX3721@outlook.com
License: MIT
Project-URL: Bug Tracker, https://github.com/your_username/ankml/issues
Project-URL: Documentation, https://ankml.top/docs
Project-URL: Source Code, https://github.com/your_username/ankml
Project-URL: Website, https://ankml.top
Keywords: malware,detection,security,machine learning,artificial intelligence,cybersecurity,antivirus,neural network,deep learning,threat detection
Classifier: Development Status :: 4 - Beta
Classifier: Intended Audience :: Developers
Classifier: Intended Audience :: Information Technology
Classifier: Intended Audience :: Science/Research
Classifier: License :: OSI Approved :: MIT License
Classifier: Operating System :: OS Independent
Classifier: Programming Language :: Python :: 3
Classifier: Programming Language :: Python :: 3.8
Classifier: Programming Language :: Python :: 3.9
Classifier: Programming Language :: Python :: 3.10
Classifier: Programming Language :: Python :: 3.11
Classifier: Topic :: Security
Classifier: Topic :: Scientific/Engineering :: Artificial Intelligence
Classifier: Topic :: Software Development :: Libraries :: Python Modules
Requires-Python: >=3.8
Requires-Dist: Flask==2.3.3
Requires-Dist: Werkzeug==2.3.7
Requires-Dist: Jinja2==3.1.2
Requires-Dist: MarkupSafe==2.1.3
Requires-Dist: click==8.1.7
Requires-Dist: itsdangerous==2.1.2
Requires-Dist: onnx>=1.12.0
Requires-Dist: onnxruntime>=1.13.0
Requires-Dist: cryptography>=3.4.8
Requires-Dist: requests
Requires-Dist: python-dateutil>=2.8.2
Provides-Extra: dev
Requires-Dist: pytest>=6.0; extra == "dev"
Requires-Dist: pytest-cov>=2.0; extra == "dev"
Requires-Dist: black>=21.0; extra == "dev"
Requires-Dist: flake8>=3.8; extra == "dev"
Requires-Dist: mypy>=0.800; extra == "dev"
Provides-Extra: gui
Requires-Dist: tkinter; extra == "gui"
Provides-Extra: web
Requires-Dist: flask>=2.0; extra == "web"
Requires-Dist: flask-cors>=3.0; extra == "web"
